{
  "projects": [
    {
      "id": 1,
      "projectfile": [],
      "title": "Project 1",
      "tasks": [
        {
          "question": "Chèn hình <i>'dayofweek.jpg'</i> trong thư mục <i>WORD </i> của thư mục <i>Documents</i> vào văn bản sao cho hình nằm sau nội dung '...today resemble those names.'. Thay đổi chiều ngang hình là 6.2'.",
          "answers": "",
          "image": ""
        },
        {
          "question": "Chèn ngắt phần kiểu Next Page ngay trước tiêu đề 'Facts about Saturday and Sunday'.",
          "answers": "",
          "image": ""
        },
        {
          "question": "Vẽ hình 6-Point Star bên phải chữ 'Days of the Week' ở đầu văn bản và nhập nội dung '6D' vào hình.",
          "answers": "",
          "image": ""
        },
        {
          "question": "Chèn trang bìa kiểu Filigree vào văn bản  xóa trường thông tin Address.",
          "answers": "",
          "image": ""
        },
        {
          "question": "Loại bỏ các thông tin cá nhân khỏi văn bản.",
          "answers": "",
          "image": ""
        },
        {
          "question": "Tạo thẻ đánh dấu với tên <u>'Entail'</u> cho nội dung 'Consist Tables'",
          "answers": "",
          "image": ""
        }
      ]
    },
    {
      "id": 2,
      "projectfile": [],
      "title": "Project 2",
      "tasks": [
        {
          "question": "Chèn bảng gồm 4 dòng và 5 cột vào bên dưới đoạn ‘Syllabus’ sao cho độ rộng bảng vừa cửa số.",
          "answers": "",
          "image": ""
        },
        {
          "question": "Áp dụng kiểu Grid Table 4 - Accent 3 cho bảng.",
          "answers": "",
          "image": ""
        },
        {
          "question": "Thay đổi nội dung trường Title trong dòng đầu trang thành <u>‘Desktop Support Course’</u>.",
          "answers": "",
          "image": ""
        },
        {
          "question": "Tạo thẻ đánh dấu cho tiêu đề ‘Course Length’ với tên <u>‘Time’</u>.",
          "answers": "",
          "image": ""
        }
      ]
    },
    {
      "id": 3,
      "projectfile": [],
      "title": "Project 3",
      "tasks": [
        {
          "question": "Trong thuộc tính tệp  thiết lập thông tin Category của tệp văn bản là chuỗi <b>animals</b>.",
          "answers": "",
          "image": ""
        },
        {
          "question": "Trong phần <b>Children Love Dinosaurs</b>  sao chép định dạng của đoạn đầu tiên và áp dụng cho đoạn thứ hai.",
          "answers": "",
          "image": ""
        },
        {
          "question": "Trong phần <b>Other Important Points About Dinosaurs</b>  sắp xếp dữ liệu bảng theo <b>Geological Period</b> (thứ tự tăng dần) và sau đó theo <b>Dinosaur</b> (thứ tự tăng dần).",
          "answers": "",
          "image": ""
        },
        {
          "question": "Trong phần <b>Other Important Points About Dinosaurs</b>  thay đổi cấp độ danh sách của <b>Velociraptor</b> thành <b>Cấp độ 3</b>.",
          "answers": "",
          "image": ""
        },
        {
          "question": "Trong phần <b>Favorite Dinosaurs</b>  tại đoạn văn trống ở cuối trang  sử dụng chức năng <b>Mô hình 3D</b> để chèn mô hình <b>Triceratops</b> từ thư mục <b>Documents/Word</b>.<br>Đặt mô hình theo kiểu <b>In Line with Text</b>.",
          "answers": "",
          "image": ""
        },
        {
          "question": "Trong phần <b>Other Important Points About Dinosaurs</b>  áp dụng hiệu ứng nghệ thuật <b>Pencil Sketch</b> cho <b>hình ảnh hóa thạch</b>.",
          "answers": "",
          "image": ""
        }
      ]
    },
    {
      "id": 4,
      "projectfile": [],
      "title": "Project 4",
      "tasks": [
        {
          "question": "Sao chép chuỗi “Education Degree” đến vị trí bên phải của chuỗi “Learning Theories and Skills Learned:” sao cho chuỗi văn bản vừa dán vẫn được canh trái và in đậm  in nghiêng.",
          "answers": "",
          "image": ""
        },
        {
          "question": "Áp dụng kiểu định dạng Intense Reference cho chuỗi văn bản “Introduction” trong văn bản. ",
          "answers": "",
          "image": ""
        },
        {
          "question": "Chèn sơ đồ kiểu Vertical Bullet List bên dưới đoạn văn bản “An example of this … community for donations.”. Nhập chuỗi <u>“Demonstrate”</u> vào hộp văn bản đầu tiên.",
          "answers": "",
          "image": ""
        },
        {
          "question": "Sử dụng tính năng của Word để thay thế tất cả các chuỗi “sciences” thành chuỗi <u>“knowledge”</u>.",
          "answers": "",
          "image": ""
        },
        {
          "question": "Xóa nền khỏi hình ảnh cây bút  cẩn thận không cắt bỏ bất kỳ phần nào của cây bút.",
          "answers": "",
          "image": ""
        },
        {
          "question": "Di chuyển đoạn văn bản “How can the platform help students with learning disabilities?” sao cho nó nằm phía sau đồ họa trong tài liệu.",
          "answers": "",
          "image": ""
        }
      ]
    },
    {
      "id": 5,
      "projectfile": [],
      "title": "Project 5",
      "tasks": [
        {
          "question": "Chuyển nội dung 'Planned Family Orchard' thành WordArt kiểu Fill - Gold  Accent 4  Soft Bevel.",
          "answers": "",
          "image": ""
        },
        {
          "question": "Chèn biểu tượng <u>'Copyright SignSign'</u> ngay sau nội dung 'Planned Family'.",
          "answers": "",
          "image": ""
        },
        {
          "question": "Di chuyển đoạn văn bản thứ hai sau tiêu đề “Brief overview:” sao cho nó nằm giữa hai đoạn bắt đầu từ 'Modern contraceptive  ...' đến '...barriers to accessing services '.",
          "answers": "",
          "image": ""
        },
        {
          "question": "Chèn ghi chú cuối văn bản ngay sau nội dung 'Plum' đầu tiên trong văn bản với nội dung ghi chú là <u>' A fruit of the subgenus Prunus of the genus Prunus.'</u>.",
          "answers": "",
          "image": ""
        },
        {
          "question": "Áp dụng kiểu lề trang đối xứng cho tất cả các trang trong tài liệu.",
          "answers": "",
          "image": ""
        }
      ]
    },
    {
      "id": 6,
      "projectfile": [],
      "title": "Project 6",
      "tasks": [
        {
          "question": "Thiết lập hiển thị thanh cuộn ngang  cho tài liệu.",
          "answers": "",
          "image": ""
        },   

        {
          "question": "Thêm văn bản thay thế với tiêu đề là <u>“Temperatures”</u> và nội dung mô tả là <u>'Water temperatures fluctuate'</u> cho bảng.",
          "answers": "",
          "image": ""
        },
        {
          "question": "Áp dụng kiểu định dạng Grid Table 5 Dark – Accent 1 cho bảng.",
          "answers": "",
          "image": ""
        },
        {
          "question": "Thiết lập cho tất cả các cột của bảng có độ rộng bằng nhau.",
          "answers": "",
          "image": ""
        },
        {
          "question": "Gộp tất cả các ô ở dòng cuối cùng của bảng thành 1 ô.",
          "answers": "",
          "image": ""
        }
      ]
    },
    {
      "id": 7,
      "projectfile": [],
      "title": "Project 7",
      "tasks": [
        {
          "question": "Chèn nội dung của văn bản <i>'company.docx'</i> trong thư mục <i>Word</i> của thư mục <i>Documents</i> vào văn bản ngay sau tiêu đề 'Decadent and delicious fudge'.",
          "answers": "",
          "image": ""
        },
        {
          "question": "Chèn sơ đồ kiểu Vertical Box List vào văn bản ngay sau nội dung '...to use in any fudge kettle.'.",
          "answers": "",
          "image": ""
        },
        {
          "question": "Nhập nội dung <u>Fudge/u> vào hình đầu tiên của smartArt sau đó thay đổi vị trí hình trong sơ đồ sao cho hình <u>Fudge</u> nằm ở vị trí cuối cùng.",
          "answers": "",
          "image": ""
        },
        {
          "question": "Áp dụng kiểu Intense Effect cho sơ đồ  đổi màu sơ đồ thành Colorful Range - Accent Colors 2 to 3.",
          "answers": "",
          "image": ""
        },
        {
          "question": "Chèn trang bìa kiểu Banded vào văn bản  xóa trường Company Address sau đó nhập nội dung <u>'Gourmet Fudge'</u> vào trường Document Title và <u>'TOCKIST'</u> vào trường Company Name.",
          "answers": "",
          "image": ""
        },
        {
          "question": "Thêm dòng đầu trang kiểu Facet (Even Page) cho văn bản trừ trang đầu tiên.",
          "answers": "",
          "image": ""
        }
      ]
    }
  ]
}
